[
    {
        "CodeIso2": "FR",
        "CodeIso3": "FRA",
        "Name": "FRANCE",
        "Regions": [
            {
                "CodeInsee": 84,
                "CodeISO": "FR-ARA",
                "Name": "Auvergne-Rhône-Alpes",
                "IsNew": true,
                "IsOversea": false,
                "Departments": [
                    {
                        "Name": "Ain",
                        "CodeIso": "FR-01",
                        "CodeInsee": "01",
                        "NumberOfConstituencies" : 0,
                        "Districts": []
                    },
                    {
                        "Name": "Allier",
                        "CodeIso": "FR-03",
                        "CodeInsee": "03",
                        "Constituencies": [],
                        "Towns": []
                    },
                    {
                        "Name": "Ardèche",
                        "CodeIso": "FR-07",
                        "CodeInsee": "07",
                        "NumberOfConstituencies" : 0,
                        "Districts": []
                    },
                    {
                        "Name": "Cantal",
                        "CodeIso": "FR-15",
                        "CodeInsee": "15",
                        "NumberOfConstituencies" : 0,
                        "Districts": []
                    },
                    {
                        "Name": "Drôme",
                        "CodeIso": "FR-26",
                        "CodeInsee": "26",
                        "NumberOfConstituencies" : 0,
                        "Districts": []
                    },
                    {
                        "Name": "Isère",
                        "CodeIso": "FR-38",
                        "CodeInsee": "38",
                        "NumberOfConstituencies" : 0,
                        "Districts": []
                    },
                    {
                        "Name": "Loire",
                        "CodeIso": "FR-42",
                        "CodeInsee": "42",
                        "NumberOfConstituencies" : 0,
                        "Districts": []
                    },
                    {
                        "Name": "Haute-Loire",
                        "CodeIso": "FR-43",
                        "CodeInsee": "43",
                        "NumberOfConstituencies" : 0,
                        "Districts": []
                    },
                    {
                        "Name": "Puy-de-Dôme",
                        "CodeIso": "FR-63",
                        "CodeInsee": "63",
                        "NumberOfConstituencies" : 0,
                        "Districts": []
                    },
                    {
                        "Name": "Rhône",
                        "CodeIso": "FR-69",
                        "CodeInsee": "69D",
                        "NumberOfConstituencies" : 0,
                        "Districts": []
                    },
                    {
                        "Name": "Lyon Métropole",
                        "CodeIso": "FR-69",
                        "CodeInsee": "69M",
                        "NumberOfConstituencies" : 0,
                        "Districts": []
                    },
                    {
                        "Name": "Savoie",
                        "CodeIso": "FR-73",
                        "CodeInsee": "73",
                        "NumberOfConstituencies" : 0,
                        "Districts": []
                    },
                    {
                        "Name": "Haute-Savoie",
                        "CodeIso": "FR-74",
                        "CodeInsee": "74",
                        "NumberOfConstituencies" : 0,
                        "Districts": []
                    }
                ]
            },
            {
                "CodeInsee": 27,
                "CodeISO": "FR-BFC",
                "Name": "Bourgogne-Franche-Comté",
                "IsNew": true,
                "IsOversea": false,
                "Departments": [
                    {
                        "Name": "Côte-d'Or",
                        "CodeIso": "FR-21",
                        "CodeInsee": "21",
                        "NumberOfConstituencies" : 0,
                        "Districts": []
                    },
                    {
                        "Name": "Doubs",
                        "CodeIso": "FR-25",
                        "CodeInsee": "25",
                        "NumberOfConstituencies" : 0,
                        "Districts": []
                    },
                    {
                        "Name": "Jura",
                        "CodeIso": "FR-39",
                        "CodeInsee": "39",
                        "NumberOfConstituencies" : 0,
                        "Districts": []
                    },
                    {
                        "Name": "Nièvre",
                        "CodeIso": "FR-58",
                        "CodeInsee": "58",
                        "NumberOfConstituencies" : 0,
                        "Districts": []
                    },
                    {
                        "Name": "Haute-Saône",
                        "CodeIso": "FR-70",
                        "CodeInsee": "70",
                        "NumberOfConstituencies" : 0,
                        "Districts": []
                    },
                    {
                        "Name": "Saône-et-Loire",
                        "CodeIso": "FR-71",
                        "CodeInsee": "71",
                        "NumberOfConstituencies" : 0,
                        "Districts": []
                    },
                    {
                        "Name": "Yonne",
                        "CodeIso": "FR-89",
                        "CodeInsee": "89",
                        "NumberOfConstituencies" : 0,
                        "Districts": []
                    },
                    {
                        "Name": "Territoire de Belfort",
                        "CodeIso": "FR-90",
                        "CodeInsee": "90",
                        "NumberOfConstituencies" : 0,
                        "Districts": []
                    }
                ]
            },
            {
                "CodeInsee": 53,
                "CodeISO": "FR-BRE",
                "Name": "Bretagne",
                "IsNew": true,
                "IsOversea": false,
                "Departments": [
                    {
                        "Name": "Côtes-d'Armor",
                        "CodeIso": "FR-22",
                        "CodeInsee": "22",
                        "NumberOfConstituencies" : 0,
                        "Districts": []
                    },
                    {
                        "Name": "Finistère",
                        "CodeIso": "FR-29",
                        "CodeInsee": "29",
                        "NumberOfConstituencies" : 0,
                        "Districts": []
                    },
                    {
                        "Name": "Ille-et-Vilaine",
                        "CodeIso": "FR-35",
                        "CodeInsee": "35",
                        "NumberOfConstituencies" : 0,
                        "Districts": []
                    },
                    {
                        "Name": "Morbihan",
                        "CodeIso": "FR-56",
                        "CodeInsee": "56",
                        "NumberOfConstituencies" : 0,
                        "Districts": []
                    }
                ]
            },
            {
                "CodeInsee": 24,
                "CodeISO": "FR-CVL",
                "Name": "Centre-Val de Loire",
                "IsNew": true,
                "IsOversea": false,
                "Departments": [
                    {
                        "Name": "Cher",
                        "CodeIso": "FR-18",
                        "CodeInsee": "18",
                        "NumberOfConstituencies" : 0,
                        "Districts": []
                    },
                    {
                        "Name": "Eure-et-Loir",
                        "CodeIso": "FR-28",
                        "CodeInsee": "28",
                        "NumberOfConstituencies" : 0,
                        "Districts": []
                    },
                    {
                        "Name": "Indre",
                        "CodeIso": "FR-36",
                        "CodeInsee": "36",
                        "NumberOfConstituencies" : 0,
                        "Districts": []
                    },
                    {
                        "Name": "Indre-et-Loire",
                        "CodeIso": "FR-37",
                        "CodeInsee": "37",
                        "NumberOfConstituencies" : 0,
                        "Districts": []
                    },
                    {
                        "Name": "Loir-et-Cher",
                        "CodeIso": "FR-41",
                        "CodeInsee": "41",
                        "NumberOfConstituencies" : 0,
                        "Districts": []
                    },
                    {
                        "Name": "Loiret",
                        "CodeIso": "FR-45",
                        "CodeInsee": "45",
                        "NumberOfConstituencies" : 0,
                        "Districts": []
                    }
                ]
            },
            {
                "CodeInsee": 94,
                "CodeISO": "FR-CRO",
                "Name": "Corse",
                "IsNew": true,
                "IsOversea": false,
                "Departments": [
                    {
                        "Name": "Corse-du-Sud",
                        "CodeIso": "FR-2A",
                        "CodeInsee": "2A",
                        "NumberOfConstituencies" : 0,
                        "Districts": []
                    },
                    {
                        "Name": "Haute-Corse",
                        "CodeIso": "FR-2B",
                        "CodeInsee": "2B",
                        "NumberOfConstituencies" : 0,
                        "Districts": []
                    }
                ]
            },
            {
                "CodeInsee": 44,
                "CodeISO": "FR-GES",
                "Name": "Grand-Est",
                "IsNew": true,
                "IsOversea": false,
                "Departments": [
                    {
                        "Name": "Ardennes",
                        "CodeIso": "FR-08",
                        "CodeInsee": "08",
                        "NumberOfConstituencies" : 0,
                        "Districts": []
                    },
                    {
                        "Name": "Aube",
                        "CodeIso": "FR-10",
                        "CodeInsee": "10",
                        "NumberOfConstituencies" : 0,
                        "Districts": []
                    },
                    {
                        "Name": "Marne",
                        "CodeIso": "FR-51",
                        "CodeInsee": "51",
                        "NumberOfConstituencies" : 0,
                        "Districts": []
                    },
                    {
                        "Name": "Haute-Marne",
                        "CodeIso": "FR-52",
                        "CodeInsee": "52",
                        "NumberOfConstituencies" : 0,
                        "Districts": []
                    },
                    {
                        "Name": "Meurthe-et-Moselle",
                        "CodeIso": "FR-54",
                        "CodeInsee": "54",
                        "NumberOfConstituencies" : 0,
                        "Districts": []
                    },
                    {
                        "Name": "Meuse",
                        "CodeIso": "FR-55",
                        "CodeInsee": "55",
                        "NumberOfConstituencies" : 0,
                        "Districts": []
                    },
                    {
                        "Name": "Moselle",
                        "CodeIso": "FR-57",
                        "CodeInsee": "57",
                        "NumberOfConstituencies" : 0,
                        "Districts": []
                    },
                    {
                        "Name": "Bas-Rhin",
                        "CodeIso": "FR-67",
                        "CodeInsee": "67",
                        "NumberOfConstituencies" : 0,
                        "Districts": []
                    },
                    {
                        "Name": "Haut-Rhin",
                        "CodeIso": "FR-68",
                        "CodeInsee": "68",
                        "NumberOfConstituencies" : 0,
                        "Districts": []
                    },
                    {
                        "Name": "Vosges",
                        "CodeIso": "FR-88",
                        "CodeInsee": "88",
                        "NumberOfConstituencies" : 0,
                        "Districts": []
                    }
                ]
            },
            {
                "CodeInsee": 32,
                "CodeISO": "FR-HDF",
                "Name": "Hauts-de-France",
                "IsNew": true,
                "IsOversea": false,
                "Departments": [
                    {
                        "Name": "Aisne",
                        "CodeIso": "FR-02",
                        "CodeInsee": "02",
                        "NumberOfConstituencies" : 0,
                        "Districts": []
                    },
                    {
                        "Name": "Nord",
                        "CodeIso": "FR-59",
                        "CodeInsee": "59",
                        "NumberOfConstituencies" : 0,
                        "Districts": []
                    },
                    {
                        "Name": "Oise",
                        "CodeIso": "FR-60",
                        "CodeInsee": "60",
                        "NumberOfConstituencies" : 0,
                        "Districts": []
                    },
                    {
                        "Name": "Pas-de-Calais",
                        "CodeIso": "FR-62",
                        "CodeInsee": "62",
                        "NumberOfConstituencies" : 0,
                        "Districts": []
                    },
                    {
                        "Name": "Somme",
                        "CodeIso": "FR-80",
                        "CodeInsee": "80",
                        "NumberOfConstituencies" : 0,
                        "Districts": []
                    }
                ]
            },
            {
                "CodeInsee": 11,
                "CodeISO": "FR-IDF",
                "Name": "Île-de-France",
                "IsNew": true,
                "IsOversea": false,
                "Departments": [
                    {
                        "Name": "Paris",
                        "CodeIso": "FR-75",
                        "CodeInsee": "75",
                        "NumberOfConstituencies" : 0,
                        "Districts": []
                    },
                    {
                        "Name": "Seine-et-Marne",
                        "CodeIso": "FR-77",
                        "CodeInsee": "2B",
                        "NumberOfConstituencies" : 0,
                        "Districts": []
                    },
                    {
                        "Name": "Yvelines",
                        "CodeIso": "FR-78",
                        "CodeInsee": "78",
                        "NumberOfConstituencies" : 0,
                        "Districts": []
                    },
                    {
                        "Name": "Essone",
                        "CodeIso": "FR-91",
                        "CodeInsee": "91",
                        "NumberOfConstituencies" : 0,
                        "Districts": []
                    },
                    {
                        "Name": "Haut-de-Seine",
                        "CodeIso": "FR-92",
                        "CodeInsee": "92",
                        "NumberOfConstituencies" : 0,
                        "Districts": []
                    },
                    {
                        "Name": "Seine-Saint-Denis",
                        "CodeIso": "FR-93",
                        "CodeInsee": "93",
                        "NumberOfConstituencies" : 0,
                        "Districts": []
                    },
                    {
                        "Name": "Val-de-Marne",
                        "CodeIso": "FR-94",
                        "CodeInsee": "94",
                        "NumberOfConstituencies" : 0,
                        "Districts": []
                    },
                    {
                        "Name": "Val-d'Oise",
                        "CodeIso": "FR-95",
                        "CodeInsee": "95",
                        "NumberOfConstituencies" : 0,
                        "Districts": []
                    }
                ]
            },
            {
                "CodeInsee": 28,
                "CodeISO": "FR-NOR",
                "Name": "Normandie",
                "IsNew": true,
                "IsOversea": false,
                "Departments": [
                    {
                        "Name": "Calvados",
                        "CodeIso": "FR-14",
                        "CodeInsee": "14",
                        "NumberOfConstituencies" : 0,
                        "Districts": []
                    },
                    {
                        "Name": "Eure",
                        "CodeIso": "FR-27",
                        "CodeInsee": "27",
                        "NumberOfConstituencies" : 0,
                        "Districts": []
                    },
                    {
                        "Name": "Manche",
                        "CodeIso": "FR-50",
                        "CodeInsee": "50",
                        "NumberOfConstituencies" : 0,
                        "Districts": []
                    },
                    {
                        "Name": "Orne",
                        "CodeIso": "FR-61",
                        "CodeInsee": "61",
                        "NumberOfConstituencies" : 0,
                        "Districts": []

                    },
                    {
                        "Name": "Seine-Maritime",
                        "CodeIso": "FR-76",
                        "CodeInsee": "76",
                        "NumberOfConstituencies" : 0,
                        "Districts": []

                    }
                ]
            },
            {
                "CodeInsee": 75,
                "CodeISO": "FR-NAQ",
                "Name": "Nouvelle-Acquitaine",
                "IsNew": true,
                "IsOversea": false,
                "Departments": [
                    {
                        "Name": "Charente",
                        "CodeIso": "FR-16",
                        "CodeInsee": "16",
                        "NumberOfConstituencies" : 0,
                        "Districts": []

                    },
                    {
                        "Name": "Charente-Maritime",
                        "CodeIso": "FR-17",
                        "CodeInsee": "17",
                        "NumberOfConstituencies" : 0,
                        "Districts": []

                    },
                    {
                        "Name": "Corrèze",
                        "CodeIso": "FR-19",
                        "CodeInsee": "19",
                        "NumberOfConstituencies" : 0,
                        "Districts": []

                    },
                    {
                        "Name": "Creuse",
                        "CodeIso": "FR-23",
                        "CodeInsee": "23",
                        "NumberOfConstituencies" : 0,
                        "Districts": []

                    },
                    {
                        "Name": "Dordogne",
                        "CodeIso": "FR-24",
                        "CodeInsee": "24",
                        "NumberOfConstituencies" : 0,
                        "Districts": []

                    },
                    {
                        "Name": "Gironde",
                        "CodeIso": "FR-33",
                        "CodeInsee": "33",
                        "NumberOfConstituencies" : 0,
                        "Districts": []

                    },
                    {
                        "Name": "Landes",
                        "CodeIso": "FR-40",
                        "CodeInsee": "40",
                        "NumberOfConstituencies" : 0,
                        "Districts": []

                    },
                    {
                        "Name": "Lot-et-Garonne",
                        "CodeIso": "FR-47",
                        "CodeInsee": "47",
                        "NumberOfConstituencies" : 0,
                        "Districts": []

                    },
                    {
                        "Name": "Pyrénées-Atlantiques",
                        "CodeIso": "FR-64",
                        "CodeInsee": "64",
                        "NumberOfConstituencies" : 0,
                        "Districts": []

                    },
                    {
                        "Name": "Deux-Sèvres",
                        "CodeIso": "FR-79",
                        "CodeInsee": "79",
                        "NumberOfConstituencies" : 0,
                        "Districts": []

                    },
                    {
                        "Name": "Vienne",
                        "CodeIso": "FR-86",
                        "CodeInsee": "86",
                        "NumberOfConstituencies" : 0,
                        "Districts": []

                    },
                    {
                        "Name": "Haute-Vienne",
                        "CodeIso": "FR-87",
                        "CodeInsee": "87",
                        "NumberOfConstituencies" : 0,
                        "Districts": []

                    }
                ]
            },
            {
                "CodeInsee": 76,
                "CodeISO": "FR-OCC",
                "Name": "Occitanie",
                "IsNew": true,
                "IsOversea": false,
                "Departments": [
                    {
                        "Name": "Arriège",
                        "CodeIso": "FR-09",
                        "CodeInsee": "09",
                        "NumberOfConstituencies" : 0,
                        "Districts": []

                    },
                    {
                        "Name": "Aude",
                        "CodeIso": "FR-11",
                        "CodeInsee": "11",
                        "NumberOfConstituencies" : 0,
                        "Districts": []

                    },
                    {
                        "Name": "Aveyron",
                        "CodeIso": "FR-12",
                        "CodeInsee": "12",
                        "NumberOfConstituencies" : 0,
                        "Districts": []

                    },
                    {
                        "Name": "Gard",
                        "CodeIso": "FR-30",
                        "CodeInsee": "30",
                        "NumberOfConstituencies" : 0,
                        "Districts": []

                    },
                    {
                        "Name": "Haute-Garonne",
                        "CodeIso": "FR-31",
                        "CodeInsee": "31",
                        "NumberOfConstituencies" : 0,
                        "Districts": []

                    },
                    {
                        "Name": "Gers",
                        "CodeIso": "FR-32",
                        "CodeInsee": "32",
                        "NumberOfConstituencies" : 0,
                        "Districts": []

                    },
                    {
                        "Name": "Hérault",
                        "CodeIso": "FR-34",
                        "CodeInsee": "34",
                        "NumberOfConstituencies" : 0,
                        "Districts": []

                    },
                    {
                        "Name": "Lot",
                        "CodeIso": "FR-46",
                        "CodeInsee": "46",
                        "NumberOfConstituencies" : 0,
                        "Districts": []

                    },
                    {
                        "Name": "Lozère",
                        "CodeIso": "FR-48",
                        "CodeInsee": "48",
                        "NumberOfConstituencies" : 0,
                        "Districts": []

                    },
                    {
                        "Name": "Hautes-Pyrénées",
                        "CodeIso": "FR-65",
                        "CodeInsee": "65",
                        "NumberOfConstituencies" : 0,
                        "Districts": []

                    },
^                    {
                        "Name": "Pyrénées-Orientales",
                        "CodeIso": "FR-66",
                        "CodeInsee": "66",
                        "NumberOfConstituencies" : 0,
                        "Districts": []

                    },
                    {
                        "Name": "Tarn",
                        "CodeIso": "FR-81",
                        "CodeInsee": "81",
                        "NumberOfConstituencies" : 0,
                        "Districts": []

                    },
                    {
                        "Name": "Tarn-et-Garonne",
                        "CodeIso": "FR-82",
                        "CodeInsee": "82",
                        "NumberOfConstituencies" : 0,
                        "Districts": []

                    }
                ]
            },
            {
                "CodeInsee": 52,
                "CodeISO": "FR-PDL",
                "Name": "Pays de la Loire",
                "IsNew": true,
                "IsOversea": false,
                "Departments": [
                    {
                        "Name": "Loire-Atlantique",
                        "CodeIso": "FR-44",
                        "CodeInsee": "44",
                        "NumberOfConstituencies" : 0,
                        "Districts": []

                    },
                    {
                        "Name": "Maine-et-Loire",
                        "CodeIso": "FR-49",
                        "CodeInsee": "49",
                        "NumberOfConstituencies" : 0,
                        "Districts": []

                    },
                    {
                        "Name": "Mayenne",
                        "CodeIso": "FR-53",
                        "CodeInsee": "53",
                        "NumberOfConstituencies" : 0,
                        "Districts": []

                    },
                    {
                        "Name": "Sarthe",
                        "CodeIso": "FR-72",
                        "CodeInsee": "95",
                        "NumberOfConstituencies" : 0,
                        "Districts": []

                    },
                    {
                        "Name": "Vendée",
                        "CodeIso": "FR-95",
                        "CodeInsee": "85",
                        "NumberOfConstituencies" : 0,
                        "Districts": []

                    }
                ]
            },
            {
                "CodeInsee": 93,
                "CodeISO": "FR-PAC",
                "Name": "Provence-Alpes-Côte d'Azur",
                "IsNew": true,
                "IsOversea": false,
                "Departments": [
                    {
                        "Name": "Alpes-de-Haute-Provence",
                        "CodeIso": "FR-04",
                        "CodeInsee": "04",
                        "NumberOfConstituencies" : 0,
                        "Districts": []

                    },
                    {
                        "Name": "Hautes-Alpes",
                        "CodeIso": "FR-05",
                        "CodeInsee": "05",
                        "NumberOfConstituencies" : 0,
                        "Districts": []

                    },
                    {
                        "Name": "Alpes-Maritimes",
                        "CodeIso": "FR-06",
                        "CodeInsee": "06",
                        "NumberOfConstituencies" : 0,
                        "Districts": []

                    },
                    {
                        "Name": "Bouche-du-Rhône",
                        "CodeIso": "FR-13",
                        "CodeInsee": "13",
                        "NumberOfConstituencies" : 0,
                        "Districts": []

                    },
                    {
                        "Name": "Var",
                        "CodeIso": "FR-83",
                        "CodeInsee": "83",
                        "NumberOfConstituencies" : 0,
                        "Districts": []

                    },
                    {
                        "Name": "Vaucluse",
                        "CodeIso": "FR-84",
                        "CodeInsee": "84",
                        "NumberOfConstituencies" : 0,
                        "Districts": []

                    }
                ]
            },
            {
                "CodeInsee": 01,
                "CodeISO": "FR-GP",
                "Name": "Guadeloupe",
                "IsNew": true,
                "IsOversea": true,
                "Departments": [
                    {
                        "Name": "Guadeloupe",
                        "CodeIso": "GLP",
                        "CodeInsee": "971",
                        "NumberOfConstituencies" : 0,
                        "Districts": []

                    }
                ]
            },
            {
                "CodeInsee": 02,
                "CodeISO": "FR-GF",
                "Name": "Guyanne Française",
                "IsNew": true,
                "IsOversea": true,
                "Departments": [
                    {
                        "Name": "Guyanne Française",
                        "CodeIso": "GUF",
                        "CodeInsee": "973",
                        "NumberOfConstituencies" : 0,
                        "Districts": []

                    }
                ]
            },
            {
                "CodeInsee": 03,
                "CodeISO": "FR-MQ",
                "Name": "Martinique",
                "IsNew": true,
                "IsOversea": true,
                "Departments": [
                    {
                        "Name": "Martinique",
                        "CodeIso": "MTQ",
                        "CodeInsee": "972",
                        "NumberOfConstituencies" : 0,
                        "Districts": []

                    }
                ]
            },
            {
                "CodeInsee": 04,
                "CodeISO": "FR-RE",
                "Name": "Réunion",
                "IsNew": true,
                "IsOversea": true,
                "Departments": [
                    {
                        "Name": "Réunion",
                        "CodeIso": "REU",
                        "CodeInsee": "974",
                        "NumberOfConstituencies" : 0,
                        "Districts": []

                    }
                ]
            },
            {
                "CodeInsee": 06,
                "CodeISO": "FR-YT",
                "Name": "Mayotte",
                "IsNew": true,
                "IsOversea": true,
                "Departments": [
                    {
                        "Name": "Mayotte",
                        "CodeIso": "MYT",
                        "CodeInsee": "976",
                        "NumberOfConstituencies" : 0,
                        "Districts": []

                    }
                ]
            },
        ]
    }
]